matrix/__init__.py
matrix/_version.py
matrix/constant.py
matrix/diagonal.py
matrix/kronecker.py
matrix/lowrank.py
matrix/matrix.py
matrix/promote.py
matrix/shape.py
matrix/tiledblocks.py
matrix/triangular.py
matrix/util.py
matrix/woodbury.py
matrix/ops/__init__.py
matrix/ops/abs.py
matrix/ops/add.py
matrix/ops/block.py
matrix/ops/block_diag.py
matrix/ops/broadcast_batch_to.py
matrix/ops/broadcast_to.py
matrix/ops/cast.py
matrix/ops/cholesky.py
matrix/ops/cholesky_solve.py
matrix/ops/concat.py
matrix/ops/dense.py
matrix/ops/diag.py
matrix/ops/diag_extract.py
matrix/ops/divide.py
matrix/ops/dtype.py
matrix/ops/eye.py
matrix/ops/fill_diag.py
matrix/ops/inv.py
matrix/ops/iqf.py
matrix/ops/iqf_diag.py
matrix/ops/isabstract.py
matrix/ops/isnan.py
matrix/ops/kron.py
matrix/ops/logdet.py
matrix/ops/matmul.py
matrix/ops/matmul_diag.py
matrix/ops/mean.py
matrix/ops/multiply.py
matrix/ops/negative.py
matrix/ops/one.py
matrix/ops/ones.py
matrix/ops/pd_inv.py
matrix/ops/pd_schur.py
matrix/ops/power.py
matrix/ops/rank.py
matrix/ops/ratio.py
matrix/ops/reshape.py
matrix/ops/root.py
matrix/ops/sample.py
matrix/ops/schur.py
matrix/ops/shape.py
matrix/ops/shape_batch.py
matrix/ops/shape_batch_broadcast.py
matrix/ops/shape_broadcast.py
matrix/ops/shape_matrix.py
matrix/ops/shape_matrix_broadcast.py
matrix/ops/solve.py
matrix/ops/sqrt.py
matrix/ops/squeeze.py
matrix/ops/submatrix.py
matrix/ops/subtract.py
matrix/ops/sum.py
matrix/ops/take.py
matrix/ops/tile.py
matrix/ops/to_numpy.py
matrix/ops/trace.py
matrix/ops/transpose.py
matrix/ops/triangular_solve.py
matrix/ops/uprank.py
matrix/ops/util.py
matrix/ops/zero.py
matrix/ops/zeros.py
matrix/ops/algorithms/__init__.py
matrix/ops/algorithms/align.py
tests/__init__.py
tests/test_cases.py
tests/test_constant.py
tests/test_diagonal.py
tests/test_kronecker.py
tests/test_lowrank.py
tests/test_matrix.py
tests/test_promote.py
tests/test_shape.py
tests/test_tiledblocks.py
tests/test_triangular.py
tests/test_util.py
tests/test_woodbury.py
backends_matrix-1.3.0.dist-info/LICENCE.txt
backends_matrix-1.3.0.dist-info/METADATA
backends_matrix-1.3.0.dist-info/WHEEL
backends_matrix-1.3.0.dist-info/top_level.txt
backends_matrix-1.3.0.dist-info/RECORD
