Metadata-Version: 2.1
Name: backends-matrix
Version: 1.3.0
Summary: Structured matrices
Home-page: https://github.com/wesselb/matrix
Author: Wessel Bruinsma
Author-email: wessel.p.bruinsma@gmail.com
License: MIT
Requires-Python: >=3.6
License-File: LICENCE.txt
Requires-Dist: numpy (>=1.16)
Requires-Dist: plum-dispatch (>=2)
Requires-Dist: backends (>=1.4.11)
Requires-Dist: wbml (>=0.3)
Requires-Dist: algebra
